Workbook
Name rendimento_carteira: 'Meu investidor'!$C$14

Sheet Meu investidor
B12: Configurações
B13: Salário | C13: 4200
B14: Rendimento carteira | C14: 0.0089
B15: Sugestão de Investimento (30%) | C15: =C13*0.3 -> 1260
B18: INVESTIMENTO MENSAL
B19: Quanto investir por mês? | C19: 200
B20: por quantos anos? | C20: 10
B21: Taxa de rendimento mensal? (a.m) | C21: 0.0108
B22: patrimônio acumulado? | C22: =FV(C21,C20*12,C19*-1) -> 48691.533
B23: dividendos mensais? | C23: =C22*$C$14 -> 433.35465
A24: 2
A25: 5 | B25: Cenários | D25: Dividendos
A26: 10 | B26: quanto em 2 anos? | C26: =FV($C$21,$A24*12,$C$19*-1) -> 5446.1727 | D26: =C26*rendimento_carteira -> 48.470937
A27: 20 | B27: quanto em 5 anos? | C27: =FV($C$21,$A25*12,$C$19*-1) -> 16760.804 | D27: =C27*rendimento_carteira -> 149.17115
A28: 30 | B28: quanto em 10 anos? | C28: =FV($C$21,$A26*12,$C$19*-1) -> 48691.533 | D28: =C28*rendimento_carteira -> 433.35465
B29: quanto em 20 anos? | C29: =FV($C$21,$A27*12,$C$19*-1) -> 225409.8 | D29: =C29*rendimento_carteira -> 2006.1472
B30: quanto em 30 anos? | C30: =FV($C$21,$A28*12,$C$19*-1) -> 866780.96 | D30: =C30*rendimento_carteira -> 7714.3506
B33: PERFIL | C33: Conservador
B34: VALOR A SER INVESTIDO NO MÊS | C34: =C19 -> 200
B36: TIPO DE FII | C36: Percentual sugerido | D36: valores
B37: PAPEL | C37: =VLOOKUP($C$33&"-"&B37,Planilha2!$A$6:$D$24,4,FALSE) -> 0.3 | D37: =C37*$C$34 -> 60
B38: TIJOLO | C38: =VLOOKUP($C$33&"-"&B38,Planilha2!$A$6:$D$24,4,FALSE) -> 0.5 | D38: =C38*$C$34 -> 100
B39: HÍBRIDOS | C39: =VLOOKUP($C$33&"-"&B39,Planilha2!$A$6:$D$24,4,FALSE) -> 0.1 | D39: =C39*$C$34 -> 20
B40: FOFs | C40: =VLOOKUP($C$33&"-"&B40,Planilha2!$A$6:$D$24,4,FALSE) -> 0.1 | D40: =C40*$C$34 -> 20
B41: DESENVOLVIMENTO | C41: =VLOOKUP($C$33&"-"&B41,Planilha2!$A$6:$D$24,4,FALSE) -> 0 | D41: =C41*$C$34 -> 0
B42: HOTELARIAS | C42: =VLOOKUP($C$33&"-"&B42,Planilha2!$A$6:$D$24,4,FALSE) -> 0 | D42: =C42*$C$34 -> 0
D43: =SUM(D37:D42) -> 200

Sheet Planilha2
A6: CHAVE | B6: PERFIL | C6: TIPO DE FII | D6: %
A7: =$B$7&"-"&C7 -> Conservador-PAPEL | B7: Conservador | C7: PAPEL | D7: 0.3
A8: =$B$7&"-"&C8 -> Conservador-TIJOLO | B8: Conservador | C8: TIJOLO | D8: 0.5
A9: =$B$7&"-"&C9 -> Conservador-HÍBRIDOS | B9: Conservador | C9: HÍBRIDOS | D9: 0.1
A10: =$B$7&"-"&C10 -> Conservador-FOFs | B10: Conservador | C10: FOFs | D10: 0.1
A11: =$B$7&"-"&C11 -> Conservador-DESENVOLVIMENTO | B11: Conservador | C11: DESENVOLVIMENTO | D11: 0
A12: =$B$7&"-"&C12 -> Conservador-HOTELARIAS | B12: Conservador | C12: HOTELARIAS | D12: 0
A13: =$B$13&"-"&C13 -> Moderado-PAPEL | B13: Moderado | C13: PAPEL | D13: 0.32
A14: =$B$13&"-"&C14 -> Moderado-TIJOLO | B14: Moderado | C14: TIJOLO | D14: 0.35
A15: =$B$13&"-"&C15 -> Moderado-HÍBRIDOS | B15: Moderado | C15: HÍBRIDOS | D15: 0.08
A16: =$B$13&"-"&C16 -> Moderado-FOFs | B16: Moderado | C16: FOFs | D16: 0.05
A17: =$B$13&"-"&C17 -> Moderado-DESENVOLVIMENTO | B17: Moderado | C17: DESENVOLVIMENTO | D17: 0.1
A18: =$B$13&"-"&C18 -> Moderado-HOTELARIAS | B18: Moderado | C18: HOTELARIAS | D18: 0.1
A19: =$B$19&"-"&C19 -> Agressivo-PAPEL | B19: Agressivo | C19: PAPEL | D19: 0.5
A20: =$B$19&"-"&C20 -> Agressivo-TIJOLO | B20: Agressivo | C20: TIJOLO | D20: 0.1
A21: =$B$19&"-"&C21 -> Agressivo-HÍBRIDOS | B21: Agressivo | C21: HÍBRIDOS | D21: 0.05
A22: =$B$19&"-"&C22 -> Agressivo-FOFs | B22: Agressivo | C22: FOFs | D22: 0.05
A23: =$B$19&"-"&C23 -> Agressivo-DESENVOLVIMENTO | B23: Agressivo | C23: DESENVOLVIMENTO | D23: 0.2
A24: =$B$19&"-"&C24 -> Agressivo-HOTELARIAS | B24: Agressivo | C24: HOTELARIAS | D24: 0.1
